{
  "next_iteration": 207,
  "new_repo_name": "v207",
  "new_repo_url": "https://github.com/NexusPrime1112/v207",
  "current_repo": "v206",
  "snapshot_path": "data/snapshots/iter_206",
  "belief_count": 7,
  "memory_stats": {
    "beliefs": 7,
    "memories": 34,
    "interactions": 231,
    "lineage": 15,
    "performance": 2,
    "reflections": 5,
    "working_memory": 2,
    "selector_strategies": 0,
    "source_assets": 6299,
    "posted_sources": 122,
    "engaged_sources": 742
  },
  "codex_purpose": "Operational memory scaffold for Nexus Prime.",
  "ancestor_repo": "v206",
  "private_repo": false
}